dinomn/__init__.py
dinomn/detection.py
dinomn/evaluation.py
dinomn/mnds.py
dinomn/mnmodel.py
dinomn/prediction.py
dinomn/training_model.py
dinomn/.cache/torch/hub/trusted_list
dinomn/.cache/torch/hub/checkpoints/dinov2_vits14_reg4_pretrain.pth
dinomn/.cache/torch/hub/facebookresearch_dinov2_main/.gitignore
dinomn/.cache/torch/hub/facebookresearch_dinov2_main/CODE_OF_CONDUCT.md
dinomn/.cache/torch/hub/facebookresearch_dinov2_main/CONTRIBUTING.md
dinomn/.cache/torch/hub/facebookresearch_dinov2_main/LICENSE
dinomn/.cache/torch/hub/facebookresearch_dinov2_main/MODEL_CARD.md
dinomn/.cache/torch/hub/facebookresearch_dinov2_main/README.md
dinomn/.cache/torch/hub/facebookresearch_dinov2_main/conda-extras.yaml
dinomn/.cache/torch/hub/facebookresearch_dinov2_main/conda.yaml
dinomn/.cache/torch/hub/facebookresearch_dinov2_main/hubconf.py
dinomn/.cache/torch/hub/facebookresearch_dinov2_main/pyproject.toml
dinomn/.cache/torch/hub/facebookresearch_dinov2_main/requirements-dev.txt
dinomn/.cache/torch/hub/facebookresearch_dinov2_main/requirements-extras.txt
dinomn/.cache/torch/hub/facebookresearch_dinov2_main/requirements.txt
dinomn/.cache/torch/hub/facebookresearch_dinov2_main/setup.cfg
dinomn/.cache/torch/hub/facebookresearch_dinov2_main/setup.py
dinomn/.cache/torch/hub/facebookresearch_dinov2_main/.github/workflows/lint.yaml
dinomn/.cache/torch/hub/facebookresearch_dinov2_main/dinov2/__init__.py
dinomn/.cache/torch/hub/facebookresearch_dinov2_main/dinov2/configs/__init__.py
dinomn/.cache/torch/hub/facebookresearch_dinov2_main/dinov2/configs/ssl_default_config.yaml
dinomn/.cache/torch/hub/facebookresearch_dinov2_main/dinov2/configs/eval/vitb14_pretrain.yaml
dinomn/.cache/torch/hub/facebookresearch_dinov2_main/dinov2/configs/eval/vitb14_reg4_pretrain.yaml
dinomn/.cache/torch/hub/facebookresearch_dinov2_main/dinov2/configs/eval/vitg14_pretrain.yaml
dinomn/.cache/torch/hub/facebookresearch_dinov2_main/dinov2/configs/eval/vitg14_reg4_pretrain.yaml
dinomn-0.0.0.2.dist-info/METADATA
dinomn-0.0.0.2.dist-info/WHEEL
dinomn-0.0.0.2.dist-info/licenses/LICENSE
dinomn-0.0.0.2.dist-info/RECORD
